starlette_http_exceptions/__init__.py
starlette_http_exceptions/http_exceptions.py
starlette_http_exceptions/status.py
starlette_http_exceptions/ws_exceptions.py
starlette_http_exceptions-0.1.2.dist-info/METADATA
starlette_http_exceptions-0.1.2.dist-info/WHEEL
starlette_http_exceptions-0.1.2.dist-info/top_level.txt
starlette_http_exceptions-0.1.2.dist-info/RECORD
